pm4pymdl/__init__.py
pm4pymdl/bson_converter.py
pm4pymdl/order_log_generation.py
pm4pymdl/algo/__init__.py
pm4pymdl/algo/bindings/__init__.py
pm4pymdl/algo/bindings/events.py
pm4pymdl/algo/mvp/__init__.py
pm4pymdl/algo/mvp/discovery/__init__.py
pm4pymdl/algo/mvp/discovery/algorithm.py
pm4pymdl/algo/mvp/discovery/versions/__init__.py
pm4pymdl/algo/mvp/discovery/versions/classic.py
pm4pymdl/algo/mvp/gen_framework/__init__.py
pm4pymdl/algo/mvp/gen_framework/algorithm.py
pm4pymdl/algo/mvp/gen_framework/procl_derivation_model.py
pm4pymdl/algo/mvp/gen_framework/edge_freq/__init__.py
pm4pymdl/algo/mvp/gen_framework/edge_freq/edge_freq_builder.py
pm4pymdl/algo/mvp/gen_framework/edge_freq/type11.py
pm4pymdl/algo/mvp/gen_framework/edge_freq/type12.py
pm4pymdl/algo/mvp/gen_framework/edge_freq/type13.py
pm4pymdl/algo/mvp/gen_framework/edge_freq/type211.py
pm4pymdl/algo/mvp/gen_framework/edge_freq/type212.py
pm4pymdl/algo/mvp/gen_framework/edge_freq/type221.py
pm4pymdl/algo/mvp/gen_framework/edge_freq/type222.py
pm4pymdl/algo/mvp/gen_framework/edge_freq/type231.py
pm4pymdl/algo/mvp/gen_framework/edge_freq/type232.py
pm4pymdl/algo/mvp/gen_framework/models/__init__.py
pm4pymdl/algo/mvp/gen_framework/models/basic_model_structure.py
pm4pymdl/algo/mvp/gen_framework/models/model1.py
pm4pymdl/algo/mvp/gen_framework/models/model2.py
pm4pymdl/algo/mvp/gen_framework/models/model3.py
pm4pymdl/algo/mvp/gen_framework/models/model_builder.py
pm4pymdl/algo/mvp/gen_framework/node_freq/__init__.py
pm4pymdl/algo/mvp/gen_framework/node_freq/node_freq_builder.py
pm4pymdl/algo/mvp/gen_framework/node_freq/type1.py
pm4pymdl/algo/mvp/gen_framework/node_freq/type21.py
pm4pymdl/algo/mvp/gen_framework/node_freq/type22.py
pm4pymdl/algo/mvp/gen_framework/node_freq/type23.py
pm4pymdl/algo/mvp/gen_framework/node_freq/type31.py
pm4pymdl/algo/mvp/gen_framework/node_freq/type32.py
pm4pymdl/algo/mvp/gen_framework/node_freq/type33.py
pm4pymdl/algo/mvp/gen_framework/rel_activities/__init__.py
pm4pymdl-0.0.46.dist-info/LICENSE
pm4pymdl-0.0.46.dist-info/METADATA
pm4pymdl-0.0.46.dist-info/WHEEL
pm4pymdl-0.0.46.dist-info/top_level.txt
pm4pymdl-0.0.46.dist-info/RECORD
