Metadata-Version: 2.1
Name: pm4pymdl
Version: 0.0.46
Summary: Process Mining for Python - Multi-Dimensional Event Logs
Home-page: http://www.pm4py.org
Author: PADS
Author-email: a.berti@pads.rwth-aachen.de
License: MIT
Project-URL: Documentation, http://pm4py.pads.rwth-aachen.de/documentation/
Project-URL: Source, https://github.com/pm4py/pm4py-source
Project-URL: Tracker, https://github.com/pm4py/pm4py-source/issues
Platform: UNKNOWN
License-File: LICENSE
Requires-Dist: pm4py (>=2.2.15)
Requires-Dist: pyarrow
Requires-Dist: Flask
Requires-Dist: flask-cors
Requires-Dist: setuptools
Requires-Dist: frozendict
Requires-Dist: jsonschema
Requires-Dist: plantuml
